sfdao/__init__.py
sfdao/cli/__init__.py
sfdao/cli/audit.py
sfdao/cli/main.py
sfdao/cli/progress.py
sfdao/config/__init__.py
sfdao/config/loader.py
sfdao/config/models.py
sfdao/evaluator/__init__.py
sfdao/evaluator/financial_facts.py
sfdao/evaluator/ml_utility.py
sfdao/evaluator/privacy.py
sfdao/evaluator/privacy_cli.py
sfdao/evaluator/scoring.py
sfdao/evaluator/statistical.py
sfdao/generator/__init__.py
sfdao/generator/base.py
sfdao/generator/baseline.py
sfdao/generator/ctgan.py
sfdao/generator/factory.py
sfdao/guard/base.py
sfdao/guard/engine.py
sfdao/guard/factory.py
sfdao/guard/rules/datetime.py
sfdao/guard/rules/numeric.py
sfdao/guard/rules/uniqueness.py
sfdao/ingestion/__init__.py
sfdao/ingestion/financial_domain.py
sfdao/ingestion/loader.py
sfdao/ingestion/schema.py
sfdao/ingestion/type_detector.py
sfdao/reporter/__init__.py
sfdao/reporter/base.py
sfdao/reporter/html.py
sfdao/reporter/pdf.py
sfdao/reporter/templates/report.html
sfdao/scenario/__init__.py
sfdao/scenario/engine.py
sfdao/scenario/loader.py
sfdao/scenario/models.py
sfdao/scenario/transformations.py
sfdao/scripts/benchmark_audit.py
sfdao/scripts/generate_test_synthetic_data.py
sfdao-0.1.0.dist-info/METADATA
sfdao-0.1.0.dist-info/WHEEL
sfdao-0.1.0.dist-info/entry_points.txt
sfdao-0.1.0.dist-info/licenses/LICENSE
sfdao-0.1.0.dist-info/RECORD
