Metadata-Version: 2.4
Name: sfdao
Version: 0.1.0
Summary: Synthetic Finance Data Auditor & Optimizer
License: MIT
License-File: LICENSE
Keywords: synthetic-data,finance,evaluation,privacy,auditor
Author: takurot
Author-email: takuro.tsujikawa@gmail.com
Requires-Python: >=3.10,<3.13
Classifier: Development Status :: 4 - Beta
Classifier: Intended Audience :: Financial and Insurance Industry
Classifier: Intended Audience :: Science/Research
Classifier: License :: OSI Approved :: MIT License
Classifier: Operating System :: OS Independent
Classifier: Programming Language :: Python :: 3
Classifier: Programming Language :: Python :: 3.10
Classifier: Programming Language :: Python :: 3.11
Classifier: Programming Language :: Python :: 3.12
Classifier: Topic :: Scientific/Engineering :: Artificial Intelligence
Classifier: Topic :: Security :: Cryptography
Provides-Extra: deep
Requires-Dist: jinja2 (>=3.1.6,<4.0.0)
Requires-Dist: numpy (>=1.26.4,<2.0.0)
Requires-Dist: pandas (>=2.2.3,<3.0.0)
Requires-Dist: pydantic (>=2.12.5,<3.0.0)
Requires-Dist: pyyaml (>=6.0.3,<7.0.0)
Requires-Dist: rich (>=13.9.4,<14.0.0)
Requires-Dist: scikit-learn (>=1.3,<2.0)
Requires-Dist: scipy (>=1.13.1,<2.0.0)
Requires-Dist: sdv (>=1.11.0,<2.0.0) ; extra == "deep"
Requires-Dist: typer (>=0.15.1,<0.16.0)
Requires-Dist: weasyprint (>=67.0,<68.0)
Project-URL: Homepage, https://github.com/takurot/sfdao
Project-URL: Repository, https://github.com/takurot/sfdao
